{"region":"03503a52-6d31-4131-a352-80aecb08bba6","model":{"(!DUPLICATES && !SEQUENTIAL)":2.11205E7,"(DUPLICATES && !SEQUENTIAL)":1.6032E7,"(!DUPLICATES && SEQUENTIAL)":2.63395E7,"(DUPLICATES && SEQUENTIAL)":2.1139E7},"modelToMin":{"(!DUPLICATES && !SEQUENTIAL)":0.0,"(DUPLICATES && !SEQUENTIAL)":0.0,"(!DUPLICATES && SEQUENTIAL)":5320000.0,"(DUPLICATES && SEQUENTIAL)":5296000.0},"modelToMax":{"(!DUPLICATES && !SEQUENTIAL)":6.60938E8,"(DUPLICATES && !SEQUENTIAL)":4.64214E8,"(!DUPLICATES && SEQUENTIAL)":5.01038E8,"(DUPLICATES && SEQUENTIAL)":3.84349E8},"modelToDiff":{"(!DUPLICATES && !SEQUENTIAL)":6.60938E8,"(DUPLICATES && !SEQUENTIAL)":4.64214E8,"(!DUPLICATES && SEQUENTIAL)":4.95718E8,"(DUPLICATES && SEQUENTIAL)":3.79053E8},"modelToSampleVariance":{"(!DUPLICATES && !SEQUENTIAL)":6.002803288825576E16,"(DUPLICATES && !SEQUENTIAL)":3.2654614565579636E16,"(!DUPLICATES && SEQUENTIAL)":4.224233996192244E16,"(DUPLICATES && SEQUENTIAL)":2.1722138194990932E16},"modelToConfidenceInterval":{"(!DUPLICATES && !SEQUENTIAL)":[9.307049420940909E7,2.497840557905909E8],"(DUPLICATES && !SEQUENTIAL)":[5.106255189870645E7,1.8136538560129356E8],"(!DUPLICATES && SEQUENTIAL)":[8.532172955719039E7,2.167847204428096E8],"(DUPLICATES && SEQUENTIAL)":[4.668819188986532E7,1.529636206101347E8]},"modelToCoefficientOfVariation":{"(!DUPLICATES && !SEQUENTIAL)":1.4381461653286867,"(DUPLICATES && !SEQUENTIAL)":1.5670890965115083,"(!DUPLICATES && SEQUENTIAL)":1.369146356837653,"(DUPLICATES && SEQUENTIAL)":1.4879480386634043},"modelToPerfHumanReadable":{"(!DUPLICATES && !SEQUENTIAL)":"0.0211205","(DUPLICATES && !SEQUENTIAL)":"0.0160320","(!DUPLICATES && SEQUENTIAL)":"0.0263395","(DUPLICATES && SEQUENTIAL)":"0.0211390"},"modelToMinHumanReadable":{"(!DUPLICATES && !SEQUENTIAL)":"0.0000000","(DUPLICATES && !SEQUENTIAL)":"0.0000000","(!DUPLICATES && SEQUENTIAL)":"0.0053200","(DUPLICATES && SEQUENTIAL)":"0.0052960"},"modelToMaxHumanReadable":{"(!DUPLICATES && !SEQUENTIAL)":"0.6609380","(DUPLICATES && !SEQUENTIAL)":"0.4642140","(!DUPLICATES && SEQUENTIAL)":"0.5010380","(DUPLICATES && SEQUENTIAL)":"0.3843490"},"modelToDiffHumanReadable":{"(!DUPLICATES && !SEQUENTIAL)":"0.6609380","(DUPLICATES && !SEQUENTIAL)":"0.4642140","(!DUPLICATES && SEQUENTIAL)":"0.4957180","(DUPLICATES && SEQUENTIAL)":"0.3790530"},"modelToSampleVarianceHumanReadble":{"(!DUPLICATES && !SEQUENTIAL)":"0.0600280","(DUPLICATES && !SEQUENTIAL)":"0.0326546","(!DUPLICATES && SEQUENTIAL)":"0.0422423","(DUPLICATES && SEQUENTIAL)":"0.0217221"},"modelToConfidenceIntervalHumanReadable":{"(!DUPLICATES && !SEQUENTIAL)":["0.0930705","0.2497841"],"(DUPLICATES && !SEQUENTIAL)":["0.0510626","0.1813654"],"(!DUPLICATES && SEQUENTIAL)":["0.0853217","0.2167847"],"(DUPLICATES && SEQUENTIAL)":["0.0466882","0.1529636"]},"modelToCoefficientOfVariationHumanReadable":{"(!DUPLICATES && !SEQUENTIAL)":"1.4381462","(DUPLICATES && !SEQUENTIAL)":"1.5670891","(!DUPLICATES && SEQUENTIAL)":"1.3691464","(DUPLICATES && SEQUENTIAL)":"1.4879480"}}