{"region":"861697be-056f-4724-9eb0-e52e8768578a","model":{"(MAX_MEMORY && !ENV_IS_LOCKING)":7.0772E7,"(!MAX_MEMORY && !ENV_IS_LOCKING)":7.0648E7,"(!MAX_MEMORY && ENV_IS_LOCKING)":7.07115E7,"(MAX_MEMORY && ENV_IS_LOCKING)":7.0933E7},"modelToMin":{"(MAX_MEMORY && !ENV_IS_LOCKING)":6.9818E7,"(!MAX_MEMORY && !ENV_IS_LOCKING)":6.991E7,"(!MAX_MEMORY && ENV_IS_LOCKING)":6.9706E7,"(MAX_MEMORY && ENV_IS_LOCKING)":7.0103E7},"modelToMax":{"(MAX_MEMORY && !ENV_IS_LOCKING)":7.6288E7,"(!MAX_MEMORY && !ENV_IS_LOCKING)":7.5983E7,"(!MAX_MEMORY && ENV_IS_LOCKING)":7.5977E7,"(MAX_MEMORY && ENV_IS_LOCKING)":7.6723E7},"modelToDiff":{"(MAX_MEMORY && !ENV_IS_LOCKING)":6470000.0,"(!MAX_MEMORY && !ENV_IS_LOCKING)":6073000.0,"(!MAX_MEMORY && ENV_IS_LOCKING)":6271000.0,"(MAX_MEMORY && ENV_IS_LOCKING)":6620000.0},"modelToSampleVariance":{"(MAX_MEMORY && !ENV_IS_LOCKING)":2.8069715483870967E12,"(!MAX_MEMORY && !ENV_IS_LOCKING)":2.251055323076923E12,"(!MAX_MEMORY && ENV_IS_LOCKING)":2.8926898967948716E12,"(MAX_MEMORY && ENV_IS_LOCKING)":3.796775677419355E12},"modelToConfidenceInterval":{"(MAX_MEMORY && !ENV_IS_LOCKING)":[7.077520319840842E7,7.198329680159158E7],"(!MAX_MEMORY && !ENV_IS_LOCKING)":[7.06370642370515E7,7.15967357629485E7],"(!MAX_MEMORY && ENV_IS_LOCKING)":[7.080233566170718E7,7.189021433829282E7],"(MAX_MEMORY && ENV_IS_LOCKING)":[7.115847941685773E7,7.256352058314227E7]},"modelToCoefficientOfVariation":{"(MAX_MEMORY && !ENV_IS_LOCKING)":0.023655207695787977,"(!MAX_MEMORY && !ENV_IS_LOCKING)":0.021228834938702992,"(!MAX_MEMORY && ENV_IS_LOCKING)":0.02398752991131117,"(MAX_MEMORY && ENV_IS_LOCKING)":0.027327125643269678},"modelToPerfHumanReadable":{"(MAX_MEMORY && !ENV_IS_LOCKING)":"0.0707720","(!MAX_MEMORY && !ENV_IS_LOCKING)":"0.0706480","(!MAX_MEMORY && ENV_IS_LOCKING)":"0.0707115","(MAX_MEMORY && ENV_IS_LOCKING)":"0.0709330"},"modelToMinHumanReadable":{"(MAX_MEMORY && !ENV_IS_LOCKING)":"0.0698180","(!MAX_MEMORY && !ENV_IS_LOCKING)":"0.0699100","(!MAX_MEMORY && ENV_IS_LOCKING)":"0.0697060","(MAX_MEMORY && ENV_IS_LOCKING)":"0.0701030"},"modelToMaxHumanReadable":{"(MAX_MEMORY && !ENV_IS_LOCKING)":"0.0762880","(!MAX_MEMORY && !ENV_IS_LOCKING)":"0.0759830","(!MAX_MEMORY && ENV_IS_LOCKING)":"0.0759770","(MAX_MEMORY && ENV_IS_LOCKING)":"0.0767230"},"modelToDiffHumanReadable":{"(MAX_MEMORY && !ENV_IS_LOCKING)":"0.0064700","(!MAX_MEMORY && !ENV_IS_LOCKING)":"0.0060730","(!MAX_MEMORY && ENV_IS_LOCKING)":"0.0062710","(MAX_MEMORY && ENV_IS_LOCKING)":"0.0066200"},"modelToSampleVarianceHumanReadble":{"(MAX_MEMORY && !ENV_IS_LOCKING)":"0.0000028","(!MAX_MEMORY && !ENV_IS_LOCKING)":"0.0000023","(!MAX_MEMORY && ENV_IS_LOCKING)":"0.0000029","(MAX_MEMORY && ENV_IS_LOCKING)":"0.0000038"},"modelToConfidenceIntervalHumanReadable":{"(MAX_MEMORY && !ENV_IS_LOCKING)":["0.0707752","0.0719833"],"(!MAX_MEMORY && !ENV_IS_LOCKING)":["0.0706371","0.0715967"],"(!MAX_MEMORY && ENV_IS_LOCKING)":["0.0708023","0.0718902"],"(MAX_MEMORY && ENV_IS_LOCKING)":["0.0711585","0.0725635"]},"modelToCoefficientOfVariationHumanReadable":{"(MAX_MEMORY && !ENV_IS_LOCKING)":"0.0236552","(!MAX_MEMORY && !ENV_IS_LOCKING)":"0.0212288","(!MAX_MEMORY && ENV_IS_LOCKING)":"0.0239875","(MAX_MEMORY && ENV_IS_LOCKING)":"0.0273271"}}