{
  "base": 5.61,
  "model": [
    {
      "options": [
        {
          "option": "FRACTION",
          "from": "0.9",
          "to": "0.5"
        },
        {
          "option": "SKIP_UPSCALING",
          "from": "false",
          "to": "true"
        }
      ],
      "sign": "-",
      "value": 15.79
    },
    {
      "options": [
        {
          "option": "FRACTION",
          "from": "0.9",
          "to": "0.5"
        }
      ],
      "sign": "+",
      "value": 11.99
    },
    {
      "options": [
        {
          "option": "SKIP_UPSCALING",
          "from": "false",
          "to": "true"
        }
      ],
      "sign": "-",
      "value": 2.64
    },
    {
      "options": [
        {
          "option": "DRY_RUN",
          "from": "false",
          "to": "true"
        },
        {
          "option": "FRACTION",
          "from": "0.9",
          "to": "0.5"
        }
      ],
      "sign": "-",
      "value": 11.99
    },
    {
      "options": [
        {
          "option": "DRY_RUN",
          "from": "false",
          "to": "true"
        }
      ],
      "sign": "-",
      "value": 7.38
    },
    {
      "options": [
        {
          "option": "PLATFORM",
          "from": "android",
          "to": "ios"
        },
        {
          "option": "FRACTION",
          "from": "0.9",
          "to": "0.5"
        }
      ],
      "sign": "-",
      "value": 4.87
    },
    {
      "options": [
        {
          "option": "PLATFORM",
          "from": "android",
          "to": "ios"
        }
      ],
      "sign": "-",
      "value": 4.01
    },
    {
      "options": [
        {
          "option": "ANDROID_INCLUDE_LDPI_TVDPI",
          "from": "false",
          "to": "true"
        },
        {
          "option": "FRACTION",
          "from": "0.9",
          "to": "0.5"
        }
      ],
      "sign": "+",
      "value": 1.93
    },
    {
      "options": [
        {
          "option": "ANDROID_INCLUDE_LDPI_TVDPI",
          "from": "false",
          "to": "true"
        }
      ],
      "sign": "+",
      "value": 2.77
    },
    {
      "options": [
        {
          "option": "DRY_RUN",
          "from": "false",
          "to": "true"
        },
        {
          "option": "PLATFORM",
          "from": "android",
          "to": "ios"
        }
      ],
      "sign": "+",
      "value": 4.01
    },
    {
      "options": [
        {
          "option": "PLATFORM",
          "from": "android",
          "to": "ios"
        },
        {
          "option": "SKIP_UPSCALING",
          "from": "false",
          "to": "true"
        }
      ],
      "sign": "+",
      "value": 2.64
    },
    {
      "options": [
        {
          "option": "DRY_RUN",
          "from": "false",
          "to": "true"
        },
        {
          "option": "SKIP_UPSCALING",
          "from": "false",
          "to": "true"
        }
      ],
      "sign": "+",
      "value": 2.64
    },
    {
      "options": [
        {
          "option": "ANDROID_INCLUDE_LDPI_TVDPI",
          "from": "false",
          "to": "true"
        },
        {
          "option": "PLATFORM",
          "from": "android",
          "to": "ios"
        }
      ],
      "sign": "-",
      "value": 2.77
    },
    {
      "options": [
        {
          "option": "ANDROID_INCLUDE_LDPI_TVDPI",
          "from": "false",
          "to": "true"
        },
        {
          "option": "DRY_RUN",
          "from": "false",
          "to": "true"
        }
      ],
      "sign": "-",
      "value": 2.77
    },
    {
      "options": [
        {
          "option": "ANDROID_MIPMAP_INSTEAD_OF_DRAWABLE",
          "from": "false",
          "to": "true"
        },
        {
          "option": "FRACTION",
          "from": "0.9",
          "to": "0.5"
        }
      ],
      "sign": "+",
      "value": 0.75
    }
  ]
}
