<?xml version="1.0" encoding="UTF-8"?>
<tree type="Hot Spots" threadSelection="All thread groups" threadStatus="All states" aggregationLevel="Methods" hotSpotCalculation="Self times" unprofiledClasses="Show separately">
  <hotspot leaf="false" class="edu.cmu.cs.mvelezce.perf.debug.config.core.Task" methodName="allocateSpace" methodSignature="(I)V" time="2523892" count="0" lineNumber="-1" percent="62.5">
    <node leaf="false" class="edu.cmu.cs.mvelezce.perf.debug.config.core.TaskHandler" methodName="work" methodSignature="()V" time="2523892" count="0" lineNumber="-1" percent="62.5">
      <node leaf="true" class="edu.cmu.cs.mvelezce.perf.debug.config.core.Main" methodName="main" methodSignature="([Ljava/lang/String;)V" time="2523892" count="0" lineNumber="-1" percent="62.5"/>
    </node>
  </hotspot>
  <hotspot leaf="false" class="edu.cmu.cs.mvelezce.perf.debug.config.core.Task" methodName="populate" methodSignature="(I)V" time="1516066" count="0" lineNumber="-1" percent="37.5">
    <node leaf="false" class="edu.cmu.cs.mvelezce.perf.debug.config.core.TaskHandler" methodName="populate" methodSignature="(I)V" time="1516066" count="0" lineNumber="-1" percent="37.5">
      <node leaf="false" class="edu.cmu.cs.mvelezce.perf.debug.config.core.TaskHandler" methodName="work" methodSignature="()V" time="1516066" count="0" lineNumber="-1" percent="37.5">
        <node leaf="true" class="edu.cmu.cs.mvelezce.perf.debug.config.core.Main" methodName="main" methodSignature="([Ljava/lang/String;)V" time="1516066" count="0" lineNumber="-1" percent="37.5"/>
      </node>
    </node>
  </hotspot>
</tree>