{
  "models": [
    {
      "terms": [
        {
          "options": [],
          "time": 0.83
        },
        {
          "options": [
            {
              "from": "android",
              "to": "ios",
              "option": "PLATFORM"
            },
            {
              "from": "false",
              "to": "true",
              "option": "DRY_RUN"
            }
          ],
          "time": 0.61
        },
        {
          "options": [
            {
              "from": "false",
              "to": "true",
              "option": "ANDROID_INCLUDE_LDPI_TVDPI"
            },
            {
              "from": "3",
              "to": "1",
              "option": "SCALE"
            }
          ],
          "time": -0.93
        },
        {
          "options": [
            {
              "from": "false",
              "to": "true",
              "option": "SKIP_UPSCALING"
            },
            {
              "from": "false",
              "to": "true",
              "option": "ANDROID_INCLUDE_LDPI_TVDPI"
            }
          ],
          "time": -1.1102230246251565E-16
        },
        {
          "options": [
            {
              "from": "android",
              "to": "ios",
              "option": "PLATFORM"
            },
            {
              "from": "false",
              "to": "true",
              "option": "SKIP_UPSCALING"
            }
          ],
          "time": 0.2999999999999998
        },
        {
          "options": [
            {
              "from": "false",
              "to": "true",
              "option": "ANDROID_MIPMAP_INSTEAD_OF_DRAWABLE"
            }
          ],
          "time": 0.0
        },
        {
          "options": [
            {
              "from": "android",
              "to": "ios",
              "option": "PLATFORM"
            },
            {
              "from": "3",
              "to": "1",
              "option": "SCALE"
            }
          ],
          "time": -1.34
        },
        {
          "options": [
            {
              "from": "false",
              "to": "true",
              "option": "DRY_RUN"
            },
            {
              "from": "false",
              "to": "true",
              "option": "ANDROID_MIPMAP_INSTEAD_OF_DRAWABLE"
            }
          ],
          "time": 0.0
        },
        {
          "options": [
            {
              "from": "false",
              "to": "true",
              "option": "ANDROID_INCLUDE_LDPI_TVDPI"
            },
            {
              "from": "false",
              "to": "true",
              "option": "ANDROID_MIPMAP_INSTEAD_OF_DRAWABLE"
            }
          ],
          "time": 0.0
        },
        {
          "options": [
            {
              "from": "android",
              "to": "ios",
              "option": "PLATFORM"
            }
          ],
          "time": -0.61
        },
        {
          "options": [
            {
              "from": "false",
              "to": "true",
              "option": "DRY_RUN"
            }
          ],
          "time": -0.83
        },
        {
          "options": [
            {
              "from": "false",
              "to": "true",
              "option": "ANDROID_MIPMAP_INSTEAD_OF_DRAWABLE"
            },
            {
              "from": "3",
              "to": "1",
              "option": "SCALE"
            }
          ],
          "time": -1.0100000000000002
        },
        {
          "options": [
            {
              "from": "false",
              "to": "true",
              "option": "SKIP_UPSCALING"
            },
            {
              "from": "false",
              "to": "true",
              "option": "ANDROID_MIPMAP_INSTEAD_OF_DRAWABLE"
            }
          ],
          "time": -0.12000000000000005
        },
        {
          "options": [
            {
              "from": "false",
              "to": "true",
              "option": "SKIP_UPSCALING"
            },
            {
              "from": "3",
              "to": "1",
              "option": "SCALE"
            }
          ],
          "time": -2.3
        },
        {
          "options": [
            {
              "from": "android",
              "to": "ios",
              "option": "PLATFORM"
            },
            {
              "from": "false",
              "to": "true",
              "option": "ANDROID_INCLUDE_LDPI_TVDPI"
            }
          ],
          "time": -0.43000000000000005
        },
        {
          "options": [
            {
              "from": "false",
              "to": "true",
              "option": "SKIP_UPSCALING"
            }
          ],
          "time": -0.29999999999999993
        },
        {
          "options": [
            {
              "from": "false",
              "to": "true",
              "option": "ANDROID_INCLUDE_LDPI_TVDPI"
            }
          ],
          "time": 0.43000000000000005
        },
        {
          "options": [
            {
              "from": "false",
              "to": "true",
              "option": "DRY_RUN"
            },
            {
              "from": "3",
              "to": "1",
              "option": "SCALE"
            }
          ],
          "time": -1.77
        },
        {
          "options": [
            {
              "from": "3",
              "to": "1",
              "option": "SCALE"
            }
          ],
          "time": 1.77
        },
        {
          "options": [
            {
              "from": "android",
              "to": "ios",
              "option": "PLATFORM"
            },
            {
              "from": "false",
              "to": "true",
              "option": "ANDROID_MIPMAP_INSTEAD_OF_DRAWABLE"
            }
          ],
          "time": 0.0
        },
        {
          "options": [
            {
              "from": "false",
              "to": "true",
              "option": "DRY_RUN"
            },
            {
              "from": "false",
              "to": "true",
              "option": "ANDROID_INCLUDE_LDPI_TVDPI"
            }
          ],
          "time": -0.43000000000000005
        },
        {
          "options": [
            {
              "from": "false",
              "to": "true",
              "option": "DRY_RUN"
            },
            {
              "from": "false",
              "to": "true",
              "option": "SKIP_UPSCALING"
            }
          ],
          "time": 0.29999999999999993
        }
      ],
      "name": "default"
    },
    {
      "terms": [
        {
          "options": [
            {
              "from": "1",
              "to": "3",
              "option": "SCALE"
            }
          ],
          "time": -1.77
        },
        {
          "options": [
            {
              "from": "android",
              "to": "ios",
              "option": "PLATFORM"
            },
            {
              "from": "false",
              "to": "true",
              "option": "SKIP_UPSCALING"
            }
          ],
          "time": 1.9500000000000002
        },
        {
          "options": [
            {
              "from": "false",
              "to": "true",
              "option": "DRY_RUN"
            },
            {
              "from": "false",
              "to": "true",
              "option": "ANDROID_MIPMAP_INSTEAD_OF_DRAWABLE"
            }
          ],
          "time": 1.0100000000000002
        },
        {
          "options": [
            {
              "from": "android",
              "to": "ios",
              "option": "PLATFORM"
            },
            {
              "from": "false",
              "to": "true",
              "option": "ANDROID_MIPMAP_INSTEAD_OF_DRAWABLE"
            }
          ],
          "time": 0.3600000000000003
        },
        {
          "options": [
            {
              "from": "false",
              "to": "true",
              "option": "DRY_RUN"
            },
            {
              "from": "false",
              "to": "true",
              "option": "SKIP_UPSCALING"
            }
          ],
          "time": 2.6
        },
        {
          "options": [
            {
              "from": "false",
              "to": "true",
              "option": "ANDROID_INCLUDE_LDPI_TVDPI"
            }
          ],
          "time": -0.5
        },
        {
          "options": [
            {
              "from": "android",
              "to": "ios",
              "option": "PLATFORM"
            },
            {
              "from": "false",
              "to": "true",
              "option": "DRY_RUN"
            }
          ],
          "time": 1.9500000000000002
        },
        {
          "options": [
            {
              "from": "false",
              "to": "true",
              "option": "SKIP_UPSCALING"
            },
            {
              "from": "false",
              "to": "true",
              "option": "ANDROID_MIPMAP_INSTEAD_OF_DRAWABLE"
            }
          ],
          "time": 1.0100000000000002
        },
        {
          "options": [
            {
              "from": "android",
              "to": "ios",
              "option": "PLATFORM"
            }
          ],
          "time": -1.9500000000000002
        },
        {
          "options": [
            {
              "from": "false",
              "to": "true",
              "option": "ANDROID_MIPMAP_INSTEAD_OF_DRAWABLE"
            },
            {
              "from": "1",
              "to": "3",
              "option": "SCALE"
            }
          ],
          "time": 1.0100000000000002
        },
        {
          "options": [
            {
              "from": "false",
              "to": "true",
              "option": "ANDROID_INCLUDE_LDPI_TVDPI"
            },
            {
              "from": "false",
              "to": "true",
              "option": "ANDROID_MIPMAP_INSTEAD_OF_DRAWABLE"
            }
          ],
          "time": 0.0
        },
        {
          "options": [
            {
              "from": "false",
              "to": "true",
              "option": "ANDROID_MIPMAP_INSTEAD_OF_DRAWABLE"
            }
          ],
          "time": -1.0100000000000002
        },
        {
          "options": [
            {
              "from": "android",
              "to": "ios",
              "option": "PLATFORM"
            },
            {
              "from": "1",
              "to": "3",
              "option": "SCALE"
            }
          ],
          "time": 1.3400000000000003
        },
        {
          "options": [
            {
              "from": "false",
              "to": "true",
              "option": "DRY_RUN"
            },
            {
              "from": "1",
              "to": "3",
              "option": "SCALE"
            }
          ],
          "time": 1.77
        },
        {
          "options": [
            {
              "from": "false",
              "to": "true",
              "option": "SKIP_UPSCALING"
            }
          ],
          "time": -2.6
        },
        {
          "options": [
            {
              "from": "android",
              "to": "ios",
              "option": "PLATFORM"
            },
            {
              "from": "false",
              "to": "true",
              "option": "ANDROID_INCLUDE_LDPI_TVDPI"
            }
          ],
          "time": -0.1499999999999999
        },
        {
          "options": [
            {
              "from": "false",
              "to": "true",
              "option": "DRY_RUN"
            },
            {
              "from": "false",
              "to": "true",
              "option": "ANDROID_INCLUDE_LDPI_TVDPI"
            }
          ],
          "time": 0.5
        },
        {
          "options": [
            {
              "from": "false",
              "to": "true",
              "option": "SKIP_UPSCALING"
            },
            {
              "from": "1",
              "to": "3",
              "option": "SCALE"
            }
          ],
          "time": 2.3
        },
        {
          "options": [
            {
              "from": "false",
              "to": "true",
              "option": "DRY_RUN"
            }
          ],
          "time": -2.6
        },
        {
          "options": [
            {
              "from": "false",
              "to": "true",
              "option": "ANDROID_INCLUDE_LDPI_TVDPI"
            },
            {
              "from": "1",
              "to": "3",
              "option": "SCALE"
            }
          ],
          "time": 0.9299999999999999
        },
        {
          "options": [
            {
              "from": "false",
              "to": "true",
              "option": "SKIP_UPSCALING"
            },
            {
              "from": "false",
              "to": "true",
              "option": "ANDROID_INCLUDE_LDPI_TVDPI"
            }
          ],
          "time": 0.5
        },
        {
          "options": [],
          "time": 2.6
        }
      ],
      "name": "user"
    }
  ]
}
